{
  "general": {
    "default_input_directory": "",
    "default_output_directory": "",
    "theme": "system",
    "language": "ko",
    "check_updates_on_startup": true,
    "auto_scan": true,
    "confirm_before_organize": true
  },
  "organization": {
    "create_series_folders": true,
    "create_season_folders": true,
    "preserve_original_extension": true,
    "move_subtitles": true,
    "duplicate_handling": "ask",
    "series_folder_pattern": "{series_name}",
    "season_folder_pattern": "Season {season_number}",
    "episode_file_pattern": "{series_name} - S{season_number}E{episode_number} - {episode_title}",
    "movie_file_pattern": "{title} ({year})"
  },
  "api": {
    "tmdb": {
      "enabled": true,
      "api_key": "",
      "language": "ko-KR"
    },
    "anilist": {
      "enabled": true,
      "client_id": "",
      "client_secret": ""
    },
    "opensubtitles": {
      "enabled": false,
      "username": "",
      "password": ""
    }
  },
  "advanced": {
    "scan_excluded_directories": [".git", "__pycache__", "venv", "env"],
    "video_extensions": [".mp4", ".mkv", ".avi", ".mov", ".wmv", ".flv", ".webm", ".m4v"],
    "subtitle_extensions": [".srt", ".ass", ".ssa", ".vtt", ".sub"],
    "logging_level": "INFO",
    "hash_chunk_size": 65536,
    "max_hash_size": 104857600
  }
} 